{"state":{"token":"eyJhbGciOiJIUzI1NiIsInR5cCI6IkpXVCJ9.eyJ1c2VySWQiOjU1NTQ1MSwidGltZXN0YW1wIjoxNzE2OTAzNDI4OTkwLCJ0eXBlIjoxLCJpYXQiOjE3MTY5MDM0MjgsImV4cCI6MTcxNzUwODIyOH0.syRjyFyatqm_imyJkwbj7AjO9iAHI5zdkBav_Pyu-Fc","userInfo":{"id":555451,"email":null,"mobile":null,"username":null,"address":null,"avatar":"https://quackquack-prj.s3.ap-southeast-1.amazonaws.com/avatar/default.jpg","fullName":null,"status":2,"lastActive":null,"type":1,"referralCode":"f3MbHpLC1R","telegramId":5611152837,"telegramData":{"id":5611152837,"username":"truogd","lastName":"Quang","firstName":"Nguyễn","languageCode":"vi","allowsWriteToPm":true},"createdTime":"2024-05-27T00:17:53.938Z","updatedTime":"2024-05-27T00:17:53.938Z","googleId":null,"facebookId":null,"fileId":null,"tier":1,"twitterId":null,"twitterData":null,"twitterAccessToken":null}},"version":0}